ljs_example_pkg/__init__.py
ljs_example_pkg/server.py
ljs_example_pkg-0.1.32.dist-info/METADATA
ljs_example_pkg-0.1.32.dist-info/WHEEL
ljs_example_pkg-0.1.32.dist-info/entry_points.txt
ljs_example_pkg-0.1.32.dist-info/RECORD
