Metadata-Version: 2.4
Name: ljs-example-pkg
Version: 0.1.32
Summary: Add your description here
Author-email: lijunshi <lijunshi2015@163.com>
Requires-Python: >=3.11
Requires-Dist: mcp[cli]>=1.6.0
Requires-Dist: pymysql>=1.1.1
Requires-Dist: python-dotenv>=1.1.0
Requires-Dist: requests>=2.32.3
